conductor/__init__.py
conductor/constants.py
conductor/key_storage.py
conductor/load_api_keys.py
conductor/utils.py
conductor/cli/__init__.py
conductor/cli/setup.py
conductor/generator/__init__.py
conductor/generator/init_project.py
conductor/generator/init_project/__init__.py
conductor/generator/init_project/design_draft.py
conductor/generator/init_project/generator_commands.py
conductor/generator/init_project/metro_docs/base_model_examples.md
conductor/generator/init_project/metro_docs/controller_lifecycle.md
conductor/generator/init_project/metro_docs/generator_commands.md
conductor/llms/__init__.py
conductor/llms/completion.py
metro/__init__.py
metro/app.py
metro/background.py
metro/config.py
metro/controllers.py
metro/exceptions.py
metro/logger.py
metro/middleware.py
metro/params.py
metro/requests.py
metro/responses.py
metro/routing.py
metro/websockets.py
metro/admin/__init__.py
metro/admin/admin_auth_controller.py
metro/admin/admin_panel_controller.py
metro/admin/find_auth_class.py
metro/admin/templates/__init__.py
metro/auth/__init__.py
metro/auth/helpers.py
metro/auth/api_key/__init__.py
metro/auth/api_key/api_key_base.py
metro/auth/api_key/generic_rate_limiter.py
metro/auth/api_key/rate_limiting.py
metro/auth/user/__init__.py
metro/auth/user/rate_limiter.py
metro/auth/user/user_base.py
metro/auth/user/mixins/__init__.py
metro/auth/user/mixins/email_verification_mixin.py
metro/auth/user/mixins/oauth_mixin.py
metro/auth/user/mixins/role_permission_mixin.py
metro/auth/user/mixins/two_factor_auth_mixin.py
metro/auth/user/mixins/typing.py
metro/cli/__init__.py
metro/cli/plugins.py
metro/cli/utils.py
metro/cli/commands/__init__.py
metro/cli/commands/admin.py
metro/cli/commands/db.py
metro/cli/commands/project.py
metro/cli/commands/run.py
metro/cli/commands/generate/__init__.py
metro/cli/commands/generate/controller.py
metro/cli/commands/generate/job.py
metro/cli/commands/generate/model.py
metro/cli/commands/generate/scaffold.py
metroapi-0.0.12.dist-info/licenses/LICENSE
metroapi-0.0.12.dist-info/METADATA
metroapi-0.0.12.dist-info/WHEEL
metroapi-0.0.12.dist-info/entry_points.txt
metroapi-0.0.12.dist-info/top_level.txt
metroapi-0.0.12.dist-info/RECORD
