Metadata-Version: 2.4
Name: metroapi
Version: 0.0.12
Summary: Metro: A batteries-included web framework for the fastest development experience.
Home-page: https://github.com/ricardo-agz/metro
Author: Ricardo Gonzalez
Author-email: ricardo@rgon.me
Keywords: web,framework,api
Classifier: Programming Language :: Python :: 3
Classifier: License :: OSI Approved :: MIT License
Classifier: Operating System :: OS Independent
Classifier: Development Status :: 3 - Alpha
Classifier: Intended Audience :: Developers
Classifier: Topic :: Internet :: WWW/HTTP :: WSGI :: Application
Classifier: Topic :: Software Development :: Libraries :: Application Frameworks
Requires-Python: >=3.9
License-File: LICENSE
Requires-Dist: fastapi<1.0.0,>=0.68.0
Requires-Dist: mongoengine<0.30,>=0.29.1
Requires-Dist: pymongo<4.9
Requires-Dist: uvicorn>=0.15.0
Requires-Dist: click>=8.0.0
Requires-Dist: inflect>=5.3.0
Requires-Dist: python-dotenv>=0.19.0
Requires-Dist: cryptography>=35.0.0
Requires-Dist: websockets>=10.0
Requires-Dist: bcrypt>=3.2.0
Requires-Dist: jinja2>=3.0.0
Requires-Dist: pyjwt~=2.10.1
Requires-Dist: certifi>=2024.12.14
Requires-Dist: python-multipart~=0.0.20
Requires-Dist: black~=24.10.0
Requires-Dist: isort~=5.13.2
Provides-Extra: conductor
Requires-Dist: openai~=1.59.5; extra == "conductor"
Requires-Dist: anthropic~=0.42.0; extra == "conductor"
Requires-Dist: keyring>=24.0.0; extra == "conductor"
Requires-Dist: inquirer>=3.1.3; extra == "conductor"
Dynamic: author
Dynamic: author-email
Dynamic: classifier
Dynamic: description
Dynamic: description-content-type
Dynamic: home-page
Dynamic: keywords
Dynamic: license-file
Dynamic: provides-extra
Dynamic: requires-dist
Dynamic: requires-python
Dynamic: summary
